parti_pytorch/__init__.py
parti_pytorch/optimizer.py
parti_pytorch/parti_pytorch.py
parti_pytorch/t5.py
parti_pytorch/version.py
parti_pytorch/vit_vqgan.py
parti_pytorch/vit_vqgan_trainer.py
parti_pytorch-0.2.0.dist-info/LICENSE
parti_pytorch-0.2.0.dist-info/METADATA
parti_pytorch-0.2.0.dist-info/WHEEL
parti_pytorch-0.2.0.dist-info/top_level.txt
parti_pytorch-0.2.0.dist-info/RECORD
