Metadata-Version: 2.1
Name: parti-pytorch
Version: 0.2.0
Summary: Parti - Pathways Autoregressive Text-to-Image Model - Pytorch
Home-page: https://github.com/lucidrains/parti-pytorch
Author: Phil Wang
Author-email: lucidrains@gmail.com
License: MIT
Keywords: artificial intelligence,deep learning,transformers,attention mechanism,text-to-image
Classifier: Development Status :: 4 - Beta
Classifier: Intended Audience :: Developers
Classifier: Topic :: Scientific/Engineering :: Artificial Intelligence
Classifier: License :: OSI Approved :: MIT License
Classifier: Programming Language :: Python :: 3.6
License-File: LICENSE
Requires-Dist: einops >=0.7
Requires-Dist: einops-exts
Requires-Dist: ema-pytorch
Requires-Dist: torch >=1.6
Requires-Dist: torchvision
Requires-Dist: transformers
Requires-Dist: vector-quantize-pytorch >=1.11.8
